uci_dataset/__init__.py
uci_dataset/load_data.py
uci_dataset-0.0.7.dist-info/LICENSE
uci_dataset-0.0.7.dist-info/METADATA
uci_dataset-0.0.7.dist-info/WHEEL
uci_dataset-0.0.7.dist-info/top_level.txt
uci_dataset-0.0.7.dist-info/RECORD
