Metadata-Version: 2.1
Name: uci-dataset
Version: 0.0.7
Summary: Read UCI dataset without the need to download any file from an external website.
Home-page: https://github.com/maryami66/uci-dataset
Author: Maryam Bahrami
Author-email: maryami_66@yahoo.com
License: MIT
Keywords: uci dataset,toy dataset,public dataset
Platform: UNKNOWN
Classifier: Programming Language :: Python :: 3.9
Classifier: License :: OSI Approved :: MIT License
Classifier: Operating System :: OS Independent
Requires-Python: >=3.6
Requires-Dist: scikit-learn (>=0.22.0)
Requires-Dist: numpy
Requires-Dist: rarfile
Requires-Dist: pandas (>=0.13)
Requires-Dist: scipy (>=1.4.1)
Requires-Dist: xlrd (>=1.0.0)
